behresp/__init__.py
behresp/behavior.py
behresp/conftest.py
behresp-0.11.0.dist-info/LICENSE.md
behresp-0.11.0.dist-info/METADATA
behresp-0.11.0.dist-info/WHEEL
behresp-0.11.0.dist-info/top_level.txt
behresp-0.11.0.dist-info/RECORD
