Metadata-Version: 2.1
Name: behresp
Version: 0.11.0
Summary: behresp
Home-page: https://github.com/PSLmodels/Behavioral-Responses
Download-URL: https://github.com/PSLmodels/Behavioral-Responses
License: CC0 1.0 Universal (CC0 1.0) Public Domain Dedication
Platform: UNKNOWN
Classifier: Development Status :: 4 - Beta
Classifier: Intended Audience :: Developers
Classifier: Natural Language :: English
Classifier: License :: CC0 1.0 Universal (CC0 1.0) Public Domain Dedication
Classifier: Operating System :: OS Independent
Classifier: Programming Language :: Python
Classifier: Programming Language :: Python :: 3
Classifier: Programming Language :: Python :: 3.6
Classifier: Programming Language :: Python :: 3.7
Classifier: Programming Language :: Python :: 3.8
Classifier: Topic :: Software Development :: Libraries :: Python Modules
License-File: LICENSE.md
Requires-Dist: numpy
Requires-Dist: pandas
Requires-Dist: taxcalc
